mobtexting/__init__.py
mobtexting/client.py
src/__init__.py
src/client.py
mobtexting_python-0.0.1.dist-info/METADATA
mobtexting_python-0.0.1.dist-info/WHEEL
mobtexting_python-0.0.1.dist-info/top_level.txt
mobtexting_python-0.0.1.dist-info/RECORD
