Metadata-Version: 2.1
Name: mobtexting-python
Version: 0.0.1
Summary: Python plugin to send sms using mobtexting
Home-page: UNKNOWN
Author: vishalknishad
Author-email: vishal.n@mobtexing.com
License: UNKNOWN
Platform: UNKNOWN
Classifier: Programming Language :: Python :: 2.7
Classifier: License :: OSI Approved :: MIT License
Classifier: Operating System :: OS Independent
Requires-Dist: requests
